baico/__init__.py
baico/base.py
baico/best_arm_identification.py
baico/grasp.py
baico/greedy.py
baico/incremental_beam_search.py
baico/stochastic_greedy.py
baico-0.1.0.dist-info/LICENSE
baico-0.1.0.dist-info/METADATA
baico-0.1.0.dist-info/WHEEL
baico-0.1.0.dist-info/top_level.txt
baico-0.1.0.dist-info/RECORD
